bio_data_to_db-0.1.5.dist-info/METADATA
bio_data_to_db-0.1.5.dist-info/WHEEL
bio_data_to_db-0.1.5.dist-info/entry_points.txt
bio_data_to_db-0.1.5.dist-info/licenses/LICENSE
bio_data_to_db/cli/uniprot.py
bio_data_to_db/cli/__init__.py
bio_data_to_db/cli/bindingdb.py
bio_data_to_db/cli/main.py
bio_data_to_db/py.typed
bio_data_to_db/utils/log.py
bio_data_to_db/utils/smiles.py
bio_data_to_db/utils/fasta.py
bio_data_to_db/utils/postgresql.py
bio_data_to_db/utils/__init__.py
bio_data_to_db/utils/polars.py
bio_data_to_db/bio_data_to_db.pyi
bio_data_to_db/__init__.py
bio_data_to_db/uniprot/utils.py
bio_data_to_db/uniprot/__init__.py
bio_data_to_db/bindingdb/fix_tables.py
bio_data_to_db/bindingdb/__init__.py
bio_data_to_db/bio_data_to_db.cpython-311-powerpc64le-linux-gnu.so
bio_data_to_db-0.1.5.dist-info/RECORD
