Metadata-Version: 2.3
Name: bio-data-to-db
Version: 0.1.5
Classifier: Programming Language :: Rust
Classifier: Programming Language :: Python :: Implementation :: CPython
Classifier: Programming Language :: Python :: Implementation :: PyPy
Classifier: Programming Language :: Python
Classifier: Programming Language :: Python :: 3
Classifier: Programming Language :: Python :: 3.10
Classifier: Programming Language :: Python :: 3.11
Classifier: Programming Language :: Python :: 3.12
Classifier: License :: OSI Approved :: Apache Software License
Requires-Dist: typer >=0.12.4
Requires-Dist: polars >=1.2.0
Requires-Dist: pandas >=2.0.0
Requires-Dist: sqlalchemy >=2.0.0
Requires-Dist: psycopg >=3.2.0
Requires-Dist: psycopg2-binary >=2.9.0
Requires-Dist: pyarrow >=17.0.0
License-File: LICENSE
Summary: Create DB from bio data
Author: Kiyoon Kim
License: Apache-2.0
Requires-Python: >=3.10
Project-URL: Homepage, https://github.com/deargen/bio-data-to-db
